elstir/__init__.py
elstir/__main__.py
elstir/exceptions.py
elstir/plugins.py
elstir/theme.py
elstir/commands/__init__.py
elstir/commands/autodoc.py
elstir/commands/build.py
elstir/commands/gh_deploy.py
elstir/commands/new.py
elstir/commands/serve.py
elstir/commands/simple.py
elstir/config/__init__.py
elstir/config/base.py
elstir/config/config_options.py
elstir/config/defaults.py
elstir/contrib/__init__.py
elstir/contrib/exclude.py
elstir/contrib/external_meta.py
elstir/contrib/tags.py
elstir/contrib/gallery/gallery.jinja
elstir/contrib/pandoc/__init__.py
elstir/contrib/pandoc/core.py
elstir/contrib/search/__init__.py
elstir/contrib/search/prebuild-index.js
elstir/contrib/search/search_index.py
elstir/contrib/search/lunr-language/lunr.ar.js
elstir/contrib/search/lunr-language/lunr.da.js
elstir/contrib/search/lunr-language/lunr.de.js
elstir/contrib/search/lunr-language/lunr.du.js
elstir/contrib/search/lunr-language/lunr.es.js
elstir/contrib/search/lunr-language/lunr.fi.js
elstir/contrib/search/lunr-language/lunr.fr.js
elstir/contrib/search/lunr-language/lunr.hu.js
elstir/contrib/search/lunr-language/lunr.it.js
elstir/contrib/search/lunr-language/lunr.ja.js
elstir/contrib/search/lunr-language/lunr.jp.js
elstir/contrib/search/lunr-language/lunr.multi.js
elstir/contrib/search/lunr-language/lunr.nl.js
elstir/contrib/search/lunr-language/lunr.no.js
elstir/contrib/search/lunr-language/lunr.pt.js
elstir/contrib/search/lunr-language/lunr.ro.js
elstir/contrib/search/lunr-language/lunr.ru.js
elstir/contrib/search/lunr-language/lunr.stemmer.support.js
elstir/contrib/search/lunr-language/lunr.sv.js
elstir/contrib/search/lunr-language/lunr.th.js
elstir/contrib/search/lunr-language/lunr.tr.js
elstir/contrib/search/lunr-language/lunr.vi.js
elstir/contrib/search/templates/search/lunr.js
elstir/contrib/search/templates/search/main.js
elstir/contrib/search/templates/search/worker.js
elstir/structure/__init__.py
elstir/structure/files.py
elstir/structure/nav.py
elstir-0.0.2.dist-info/LICENSE
elstir-0.0.2.dist-info/METADATA
elstir-0.0.2.dist-info/WHEEL
elstir-0.0.2.dist-info/entry_points.txt
elstir-0.0.2.dist-info/top_level.txt
elstir-0.0.2.dist-info/RECORD
